brendan_beads/__init__.py
brendan_beads/_version.py
brendan_beads/_widget.py
brendan_beads/generate_data.py
brendan_beads/napari.yaml
brendan_beads/visualize.py
brendan_beads/_tests/__init__.py
brendan_beads-0.2.dist-info/licenses/LICENSE
brendan_beads-0.2.dist-info/METADATA
brendan_beads-0.2.dist-info/WHEEL
brendan_beads-0.2.dist-info/entry_points.txt
brendan_beads-0.2.dist-info/top_level.txt
brendan_beads-0.2.dist-info/RECORD
