Metadata-Version: 2.4
Name: brendan-beads
Version: 0.2
Summary: Calculating and visualizing distances of beads to surface
Author: Anders Folkesson
Author-email: anders.folkesson@gu.se
License: 
Project-URL: Bug Tracker, https://github.com/xfolka/brendan-beads/issues
Project-URL: Documentation, https://github.com/xfolka/brendan-beads#README.md
Project-URL: Source Code, https://github.com/xfolka/brendan-beads
Project-URL: User Support, https://github.com/xfolka/brendan-beads/issues
Classifier: Development Status :: 2 - Pre-Alpha
Classifier: Framework :: napari
Classifier: Intended Audience :: Developers
Classifier: Operating System :: OS Independent
Classifier: Programming Language :: Python
Classifier: Programming Language :: Python :: 3
Classifier: Programming Language :: Python :: 3 :: Only
Classifier: Programming Language :: Python :: 3.10
Classifier: Programming Language :: Python :: 3.11
Classifier: Programming Language :: Python :: 3.12
Classifier: Programming Language :: Python :: 3.13
Classifier: Topic :: Scientific/Engineering :: Image Processing
Requires-Python: >=3.10
License-File: LICENSE
Requires-Dist: numpy
Requires-Dist: magicgui
Requires-Dist: qtpy
Requires-Dist: scikit-image
Requires-Dist: pyometiff
Provides-Extra: testing
Requires-Dist: tox; extra == "testing"
Requires-Dist: pytest; extra == "testing"
Requires-Dist: pytest-cov; extra == "testing"
Requires-Dist: pytest-qt; extra == "testing"
Requires-Dist: napari; extra == "testing"
Requires-Dist: pyqt5; extra == "testing"
Requires-Dist: numpy; extra == "testing"
Requires-Dist: pandas; extra == "testing"
Requires-Dist: matplotlib; extra == "testing"
Requires-Dist: pyometiff; extra == "testing"
Dynamic: license-file
